fpm_universe/__init__.py
fpm_universe/cli.py
fpm_universe/config.py
fpm_universe/data.py
fpm_universe/pipeline.py
fpm_universe/py.typed
fpm_universe/utils.py
factor_pricing_model_universe-2024.0.0.dist-info/LICENSE
factor_pricing_model_universe-2024.0.0.dist-info/METADATA
factor_pricing_model_universe-2024.0.0.dist-info/WHEEL
factor_pricing_model_universe-2024.0.0.dist-info/entry_points.txt
factor_pricing_model_universe-2024.0.0.dist-info/RECORD
